query_collection.py
query_collection-0.1.7.dist-info/METADATA
query_collection-0.1.7.dist-info/WHEEL
query_collection-0.1.7.dist-info/RECORD
